<?xml version="1.0" encoding="UTF-8"?>
<!DOCTYPE ConfiG PUBLIC "-//NET/ATOMIQUE/KSAR/CONFIG.DTD" "Config.dtd">
<!--
    Description:
        Configure statistics and their corresponding graphs (plots+stacks)
-->

<ConfiG>
    <OS>
        <OSType name="Linux">
            <Stat name="proc1">
                <headerstr>proc/s</headerstr>
                <graphname>PROC</graphname>
            </Stat>
            <Stat name="cswch">
                <headerstr>cswch/s</headerstr>
                <graphname>CSWCH</graphname>
            </Stat>
            <Stat name="intr">
                <headerstr>INTR intr/s</headerstr>
                <graphname>INTR</graphname>
            </Stat>
            <Stat name="swap1">
                <headerstr>pswpin/s pswpout/s</headerstr>
                <graphname>SWAP</graphname>
            </Stat>
            <Stat name="proc2">
                <headerstr>proc/s cswch/s</headerstr>
                <graphname>PROC2</graphname>
            </Stat>
            <Stat name="dev2">
                <headerstr>DEV tps blks/s</headerstr>
                <graphname>DEV_OLD</graphname>
            </Stat>
            <Stat name="page1">
                <headerstr>frmpg/s bufpg/s campg/s</headerstr>
                <graphname>PAGE</graphname>
            </Stat>
            <Stat name="page2">
                <headerstr>frmpg/s shmpg/s bufpg/s campg/s</headerstr>
                <graphname>PAGE</graphname>
            </Stat>
            <Stat name="load1">
                <headerstr>runq-sz plist-sz ldavg-1 ldavg-5</headerstr>
                <graphname>LOAD</graphname>
            </Stat>
            <Stat name="dev3">
                <headerstr>DEV tps rd_sec/s wr_sec/s</headerstr>
                <graphname>DEV</graphname>
            </Stat>
            <Stat name="paging1">
                <headerstr>pgpgin/s pgpgout/s fault/s majflt/s</headerstr>
                <graphname>PAGING</graphname>
            </Stat>
            <Stat name="dentunusd1">
                <headerstr>dentunusd file-nr inode-nr pty-nr</headerstr>
                <graphname>IGNORE</graphname>
            </Stat>
            <Stat name="cpu2">
                <headerstr>CPU %user %nice %system %idle</headerstr>
                <graphname>CPU</graphname>
            </Stat>
            <Stat name="io">
                <headerstr>tps rtps wtps bread/s bwrtn/s</headerstr>
                <graphname>IO</graphname>
            </Stat>
            <Stat name="socket1">
                <headerstr>totsck tcpsck udpsck rawsck ip-frag</headerstr>
                <graphname>SOCKET</graphname>
            </Stat>
            <Stat name="load2">
                <headerstr>runq-sz plist-sz ldavg-1 ldavg-5 ldavg-15</headerstr>
                <graphname>LOAD</graphname>
            </Stat>
            <Stat name="load_9.1.7">
                <headerstr>runq-sz plist-sz ldavg-1 ldavg-5 ldavg-15 blocked</headerstr>
                <graphname>LOAD_9.1.7</graphname>
            </Stat>
            <Stat name="kswap">
                <headerstr>kbswpfree kbswpused %swpused kbswpcad %swpcad</headerstr>
                <graphname>KSWAP</graphname>
            </Stat>
            <Stat name="cpu3">
                <headerstr>CPU %user %nice %system %iowait %idle</headerstr>
                <graphname>CPU</graphname>
            </Stat>
            <Stat name="paging2">
                <headerstr>pgpgin/s pgpgout/s activepg inadtypg inaclnpg inatarpg</headerstr>
                <graphname>PAGING</graphname>
            </Stat>
            <Stat name="nfsc">
                <headerstr>call/s retrans/s read/s write/s access/s getatt/s</headerstr>
                <graphname>NFSC</graphname>
            </Stat>
            <Stat name="socket2">
                <headerstr>totsck tcpsck udpsck rawsck ip-frag tcp-tw</headerstr>
                <graphname>SOCKET</graphname>
            </Stat>
            <Stat name="cpu4">
                <headerstr>CPU %user %nice %system %iowait %steal %idle</headerstr>
                <graphname>CPU</graphname>
            </Stat>
            <Stat name="tty">
                <headerstr>TTY rcvin/s xmtin/s framerr/s prtyerr/s brk/s ovrun/s</headerstr>
                <graphname>IGNORE</graphname>
            </Stat>
            <Stat name="kmem2">
                <headerstr>kbmemfree kbmemused %memused kbbuffers kbcached kbcommit %commit</headerstr>
                <graphname>KMEM</graphname>
            </Stat>
            <Stat name="inet10">
                <headerstr>IFACE rxpck/s txpck/s rxbyt/s txbyt/s rxcmp/s txcmp/s rxmcst/s</headerstr>
                <graphname>INET1</graphname>
            </Stat>
            <Stat name="inet11">
                <headerstr>IFACE rxpck/s txpck/s rxkB/s txkB/s rxcmp/s txcmp/s rxmcst/s</headerstr>
                <graphname>INET1</graphname>
            </Stat>
            <Stat name="inet12">
                <headerstr>IFACE rxpck/s txpck/s rxkB/s txkB/s rxcmp/s txcmp/s rxmcst/s %ifutil</headerstr>
                <graphname>INET1</graphname>
            </Stat>
            <Stat name="cpu5">
                <headerstr>CPU %usr %nice %sys %iowait %steal %irq %soft %guest %idle</headerstr>
                <graphname>CPU</graphname>
            </Stat>
            <Stat name="kmem3">
                <headerstr>kbmemfree kbmemused %memused kbmemshrd kbbuffers kbcached kbswpfree kbswpused %swpused</headerstr>
                <graphname>KMEM</graphname>
            </Stat>
            <Stat name="kmem4">
                <headerstr>kbmemfree kbmemused %memused kbbuffers kbcached kbswpfree kbswpused %swpused kbswpcad</headerstr>
                <graphname>KMEM</graphname>
            </Stat>
            <Stat name="dev4">
                <headerstr>DEV tps rd_sec/s wr_sec/s avgrq-sz avgqu-sz await svctm %util</headerstr>
                <graphname>DEV</graphname>
            </Stat>
            <Stat name="dentunusd2">
                <headerstr>dentunusd file-sz inode-sz super-sz %super-sz dquot-sz %dquot-sz rtsig-sz %rtsig-sz</headerstr>
                <graphname>IGNORE</graphname>
            </Stat>
            <Stat name="paging3">
                <headerstr>pgpgin/s pgpgout/s fault/s majflt/s pgfree/s pgscank/s pgscand/s pgsteal/s %vmeff</headerstr>
                <graphname>PAGING</graphname>
            </Stat>
            <Stat name="inet21">
                <headerstr>IFACE rxerr/s txerr/s coll/s rxdrop/s txdrop/s txcarr/s rxfram/s rxfifo/s txfifo/s</headerstr>
                <graphname>INET2</graphname>
            </Stat>
            <Stat name="dentunusd3">
                <headerstr>dentunusd file-sz %file-sz inode-sz super-sz %super-sz dquot-sz %dquot-sz rtsig-sz %rtsig-sz</headerstr>
                <graphname>IGNORE</graphname>
            </Stat>
            <Stat name="cpu6">
                <headerstr>CPU %usr %nice %sys %iowait %steal %irq %soft %guest %idle</headerstr>
                <graphname>CPU</graphname>
            </Stat>
            <Stat name="nsfm">
                <headerstr>scall/s badcall/s packet/s udp/s tcp/s hit/s miss/s sread/s swrite/s saccess/s sgetatt/s</headerstr>
                <graphname>NFSM</graphname>
            </Stat>
            <Stat name="miscip1">
                <headerstr>irec/s fwddgm/s idel/s orq/s asmrq/s asmok/s fragok/s fragcrt/s</headerstr>
                <graphname>IGNORE</graphname>
            </Stat>
            <Stat name="miscip2">
                <headerstr>irec6/s fwddgm6/s idel6/s orq6/s asmrq6/s asmok6/s imcpck6/s omcpck6/s fragok6/s fragcr6/s</headerstr>
                <graphname>IGNORE</graphname>
            </Stat>
            <Stat name="miscip3">
                <headerstr>ihdrerr/s iadrerr/s iukwnpr/s idisc/s odisc/s onort/s asmf/s fragf/s</headerstr>
                <graphname>IGNORE</graphname>
            </Stat>
            <Stat name="miscip4">
                <headerstr>imsg/s omsg/s iech/s iechr/s oech/s oechr/s itm/s itmr/s otm/s otmr/s iadrmk/s iadrmkr/s  oadrmk/s oadrmkr/s</headerstr>
                <graphname>IGNORE</graphname>
            </Stat>
            <Stat name="miscip5">
                <headerstr>ierr/s oerr/s idstunr/s odstunr/s itmex/s otmex/s iparmpb/s oparmpb/s isrcq/s osrcq/s iredir/s oredir/s</headerstr>
                <graphname>IGNORE</graphname>
            </Stat>
            <Stat name="miscip6">
                <headerstr>active/s passive/s iseg/s oseg/s</headerstr>
                <graphname>IGNORE</graphname>
            </Stat>
            <Stat name="miscip7">
                <headerstr>atmptf/s estres/s retrans/s isegerr/s orsts/s</headerstr>
                <graphname>IGNORE</graphname>
            </Stat>
            <Stat name="miscip8">
                <headerstr>idgm/s odgm/s noport/s idgmerr/s</headerstr>
                <graphname>IGNORE</graphname>
            </Stat>
            <Stat name="miscip9">
                <headerstr>active/s passive/s iseg/s oseg/s</headerstr>
                <graphname>IGNORE</graphname>
            </Stat>
            <Stat name="miscip10">
                <headerstr>imsg6/s omsg6/s iech6/s iechr6/s oechr6/s igmbq6/s  igmbr6/s ogmbr6/s igmbrd6/s ogmbrd6/s irtsol6/s ortsol6/s irtad6/s inbsol6/s onbsol6/s inbad6/s onbad6/s</headerstr>
                <graphname>IGNORE</graphname>
            </Stat>
            <Stat name="miscip11">
                <headerstr>atmptf/s estres/s retrans/s isegerr/s orsts/s</headerstr>
                <graphname>IGNORE</graphname>
            </Stat>
            <Stat name="miscip12">
                <headerstr>tcp6sck udp6sck raw6sck ip6-frag</headerstr>
                <graphname>IGNORE</graphname>
            </Stat>
            <Stat name="miscip13">
                <headerstr>irec6/s fwddgm6/s idel6/s orq6/s asmrq6/s asmok6/s imcpck6/s omcpck6/s fragok6/s fragcr6/s</headerstr>
                <graphname>IGNORE</graphname>
            </Stat>
            <Stat name="miscip14">
                <headerstr>ihdrer6/s iadrer6/s iukwnp6/s i2big6/s idisc6/s odisc6/s inort6/s onort6/s asmf6/s fragf6/s itrpck6/s</headerstr>
                <graphname>IGNORE</graphname>
            </Stat>
            <Stat name="miscip15">
                <headerstr>ierr6/s idtunr6/s odtunr6/s  itmex6/s  otmex6/s iprmpb6/s oprmpb6/s iredir6/s oredir6/s ipck2b6/s opck2b6/s</headerstr>
                <graphname>IGNORE</graphname>
            </Stat>
            <Stat name="miscip16">
                <headerstr> CPU MHz</headerstr>
                <graphname>IGNORE</graphname>
            </Stat>
            <Stat name="cpu7">
                <headerstr>CPU %usr %nice %sys %iowait %steal %irq %soft %guest %gnice %idle</headerstr>
                <graphname>CPU</graphname>
            </Stat>
            <Stat name="kmem5">
                <headerstr>kbmemfree kbmemused %memused kbbuffers kbcached kbcommit %commit kbactive kbinact kbdirty</headerstr>
                <graphname>KMEM2</graphname>
            </Stat>
            <Stat name="hpage">
                <headerstr>kbhugfree kbhugused %hugused</headerstr>
                <graphname>HPAGE</graphname>
            </Stat>

            <!-- GRAPHS -->
            <Graph name="PROC" Title="Proc" type="unique">
                <Plot Title="proc">
                    <cols>proc/s</cols>
                </Plot>
            </Graph>
            <Graph name="CSWCH" Title="Context" type="unique">
                <Plot Title="cwsch">
                    <cols>cswch/s</cols>
                </Plot>
            </Graph>

            <Graph name="INTR" Title="Interrupts" type="multiple">
                <Plot Title="intr">
                    <cols>intr/s</cols>
                </Plot>
            </Graph>
            <Graph name="SWAP" Title="Swap" type="unique">
                <Plot Title="swap">
                    <cols>pswpin/s pswpout/s</cols>
                </Plot>
            </Graph>
            <Graph name="INET1" Title="Interfaces traffic" type="multiple">
                <Plot Title="packet">
                    <cols>rxpck/s txpck/s</cols>
                </Plot>
                <Plot Title="bytes">
                    <cols>rxbyt/s txbyt/s rxkB/s txkB/s</cols>
                </Plot>
                <Plot Title="cast">
                    <cols>rxcmp/s txcmp/s rxmcst/s</cols>
                </Plot>
                <Plot Title="util">
                    <cols>%ifutil</cols>
                </Plot>
            </Graph>
            <Graph name="INET2" Title="Interfaces error" type="multiple">
                <Plot Title="Rx">
                    <cols>rxerr/s rxdrop/s rxfram/s rxfifo/s</cols>
                </Plot>
                <Plot Title="Tx">
                    <cols>txerr/s txdrop/s txcarr/s txfifo/s</cols>
                </Plot>
                <Plot Title="Collision">
                    <cols>coll/s</cols>
                </Plot>
            </Graph>
            <Graph name="PAGING" Title="Paging" type="unique">
                <Plot Title="pgp">
                    <cols>pgpgin/s pgpgout/s</cols>
                </Plot>
                <Plot Title="pg">
                    <cols>activepg inadtypg inaclnpg inatarpg</cols>
                </Plot>
                <Plot Title="fault">
                    <cols>fault/s majflt/s</cols>
                </Plot>
                <Plot Title="free">
                    <cols>pgfree/s pgscank/s pgscand/s pgsteal/s</cols>
                </Plot>
                <Plot Title="vmeff">
                    <cols>vmeff</cols>
                </Plot>
            </Graph>
            <Graph name="DEV_OLD" Title="Devices" type="multiple">
                <Plot Title="tps">
                    <cols>tps</cols>
                </Plot>
                <Plot Title="blks/s">
                    <cols>blks/s</cols>
                </Plot>
            </Graph>
            <Graph name="DEV" Title="Devices" type="multiple">
                <Plot Title="tps">
                    <cols>tps</cols>
                </Plot>
                <Plot Title="sector">
                    <cols>rd_sec/s wr_sec/s</cols>
                </Plot>
                <Plot Title="queue">
                    <cols>avgrq-sz avgqu-sz</cols>
                </Plot>
                <Plot Title="Response [ms]">
                    <cols>await</cols>
                </Plot>
            </Graph>
            <Graph name="IO" Title="I/O" type="unique">
                <Plot Title="tps">
                    <cols>tps rtps wtps</cols>
                </Plot>
                <Plot Title="blocks/s">
                    <cols>bread/s bwrtn/s</cols>
                </Plot>
            </Graph>
            <Graph name="PAGE" Title="Page" type="unique">
                <Plot Title="Page">
                    <cols>frmpg/s shmpg/s bufpg/s campg/s</cols>
                </Plot>
            </Graph>
            <Graph name="KMEM" Title="KMem" type="unique">
                <Plot Title="KMem">
                    <cols>kbmemfree kbmemused kbmemshrd kbbuffers kbcached kbcommit</cols>
                    <format base="1024" factor="1024"></format>
                </Plot>
                <Plot Title="Swap">
                    <cols>kbswpfree kbswpused kbswpcad</cols>
                    <format base="1024" factor="1024"></format>
                </Plot>
                <Plot Title="%">
                    <cols>%memused %swpused %commit</cols>
                </Plot>
            </Graph>
            <Graph name="KSWAP" Title="KSwap" type="unique">
                <Plot Title="Swap">
                    <cols>kbswpfree kbswpused kbswpcad</cols>
                    <format base="1024" factor="1024"></format>
                </Plot>
                <Plot Title="%">
                    <cols>%swpused %swpcad</cols>
                </Plot>
            </Graph>
            <Graph name="LOAD" Title="Load" type="unique">
                <Plot Title="RunQ">
                    <cols>runq-sz</cols>
                </Plot>
                <Plot Title="Plist">
                    <cols>plist-sz</cols>
                </Plot>
                <Plot Title="LA">
                    <cols>ldavg-1 ldavg-5 ldavg-15</cols>
                </Plot>
            </Graph>
            <Graph name="LOAD_9.1.7" Title="Load" type="unique">
                <Plot Title="RunQ">
                    <cols>runq-sz</cols>
                </Plot>
                <Plot Title="Plist">
                    <cols>plist-sz</cols>
                </Plot>
                <Plot Title="Load Average">
                    <cols>ldavg-1 ldavg-5 ldavg-15</cols>
                </Plot>
                <Plot Title="Tasks blocked">
                    <cols>blocked</cols>
                </Plot>
            </Graph>
            <Graph name="SOCKET" Title="Socket" type="unique">
                <Plot Title="Socket">
                    <cols>totsck tcpsck udpsck rawsck</cols>
                </Plot>
                <Plot Title="Frag">
                    <cols>ip-frag tcp-tw</cols>
                </Plot>
            </Graph>
            <Graph name="NFSC" Title="NFS Client" type="unique">
                <Plot Title="call">
                    <cols>call/s retrans/s</cols>
                </Plot>
                <Plot Title="I/O">
                    <cols>read/s write/s</cols>
                </Plot>
                <Plot Title="access">
                    <cols>access/s getatt/s</cols>
                </Plot>
            </Graph>
            <Graph name="NFSM" Title="NFS Server" type="unique">
                <Plot Title="call">
                    <cols>call/s badcalls/s</cols>
                </Plot>
                <Plot Title="I/O">
                    <cols>packet/s udp/s tcp/s</cols>
                </Plot>
                <Plot Title="cache">
                    <cols>hit/s miss/s</cols>
                </Plot>
                <Plot Title="traffic">
                    <cols>sread/s swrite/s saccess/s sgetatt/s</cols>
                </Plot>
            </Graph>
            <Graph name="PROC2" Title="Processes" type="unique">
                <Plot Title="Proc">
                    <cols>proc/s</cols>
                </Plot>
                <Plot Title="context">
                    <cols>cswch/s</cols>
                </Plot>
            </Graph>
            <Graph name="CPU" Title="CPU" type="multiple">
                <Stack Title="Used" size="3">
                    <cols>%usr %user %nice %sys %iowait %steal %irq %soft %guest</cols>
                </Stack>
                <!--
                <Plot Title="other" size="3">
                    <cols>%usr %user %nice %sys %iowait %steal %irq %soft %guest</cols>
                </Plot>
                -->
                <Plot Title="Idle" size="1">
                    <cols>%idle</cols>
                </Plot>
            </Graph>
            <Graph name="KMEM2" Title="KMem" type="unique">
                <Plot Title="KMem">
                    <cols>kbmemfree kbmemused kbbuffers kbcached kbcommit kbactive kbinact kbdirty</cols>
                    <format base="1024" factor="1024"></format>
                </Plot>
                <Plot Title="%">
                    <cols>%memused %commit</cols>
                </Plot>
            </Graph>
            <Graph name="HPAGE" Title="Hugepages" type="unique">
                <Plot Title="Hugepages">
                    <cols>kbhugfree kbhugused</cols>
                    <format base="1024" factor="1024"></format>
                </Plot>
                <Plot Title="%">
                    <cols>%hugused</cols>
                </Plot>
            </Graph>
        </OSType>
    </OS>
    <!--  END OS -->
</ConfiG>

